numerics.so
ahoy/__init__.py
ahoy/_version.py
ahoy/agents.py
ahoy/c_measurers.py
ahoy/dc_dx_measurers.py
ahoy/directions.py
ahoy/fields.py
ahoy/measurers.py
ahoy/mesh.py
ahoy/model.py
ahoy/noise_measurers.py
ahoy/numerics.c
ahoy/numerics.pyx
ahoy/numerics.so
ahoy/obstructors.py
ahoy/positions.py
ahoy/ring_buffer.py
ahoy/rudder_sets.py
ahoy/rudders.py
ahoy/ships.py
ahoy/stime.py
ahoy/swimmers.py
ahoy/turners.py
ahoy/plot/__init__.py
ahoy/plot/plot.py
ahoy/plot/plot_chi_scan.py
ahoy/plot/plot_pf_scan_drift.py
ahoy/plot/var_plot.py
ahoy/utils/__init__.py
ahoy/utils/defaults.py
ahoy/utils/paths.py
ahoy/utils/run.py
ahoy/utils/scripts.py
ahoy/utils/utils.py
ahoy-0.8.2.dist-info/DESCRIPTION.rst
ahoy-0.8.2.dist-info/entry_points.txt
ahoy-0.8.2.dist-info/METADATA
ahoy-0.8.2.dist-info/metadata.json
ahoy-0.8.2.dist-info/pbr.json
ahoy-0.8.2.dist-info/RECORD
ahoy-0.8.2.dist-info/top_level.txt
ahoy-0.8.2.dist-info/WHEEL
